lektor_limit_dependencies.py
lektor_limit_dependencies-1.0.0.dist-info/LICENSE
lektor_limit_dependencies-1.0.0.dist-info/METADATA
lektor_limit_dependencies-1.0.0.dist-info/WHEEL
lektor_limit_dependencies-1.0.0.dist-info/entry_points.txt
lektor_limit_dependencies-1.0.0.dist-info/top_level.txt
lektor_limit_dependencies-1.0.0.dist-info/RECORD
