Metadata-Version: 2.1
Name: lektor-limit-dependencies
Version: 1.0.0
Summary: Lektor plugin to limit dependencies created by queries
Author-email: Jeff Dairiki <dairiki@dairiki.org>
License: Copyright © 2020 Geoffrey T. Dairiki
Project-URL: Homepage, https://github.com/dairiki/lektor-limit-dependencies
Keywords: Lektor plugin
Classifier: Development Status :: 5 - Production/Stable
Classifier: Environment :: Plugins
Classifier: Environment :: Web Environment
Classifier: Framework :: Lektor
Classifier: Intended Audience :: Developers
Classifier: License :: OSI Approved :: MIT License
Classifier: Programming Language :: Python :: 3
Classifier: Programming Language :: Python :: 3.7
Classifier: Programming Language :: Python :: 3.8
Classifier: Programming Language :: Python :: 3.9
Classifier: Programming Language :: Python :: 3.10
Classifier: Programming Language :: Python :: 3.11
Classifier: Topic :: Text Processing
Requires-Python: >=3.7
License-File: LICENSE
Requires-Dist: lektorlib
Requires-Dist: jinja2 (>=3.0.0)
